ansible_sdk/__init__.py
ansible_sdk/_aiocompat/__init__.py
ansible_sdk/_aiocompat/csv_async.py
ansible_sdk/_aiocompat/file_async.py
ansible_sdk/_aiocompat/proxy.py
ansible_sdk/_aiocompat/receptorctl_async.py
ansible_sdk/_aiocompat/runner_async.py
ansible_sdk/_util/__init__.py
ansible_sdk/_util/dataclass_compat.py
ansible_sdk/_util/metrics.py
ansible_sdk/executors/__init__.py
ansible_sdk/executors/base.py
ansible_sdk/executors/mesh.py
ansible_sdk/executors/subprocess.py
ansible_sdk/model/__init__.py
ansible_sdk/model/job_def.py
ansible_sdk/model/job_event.py
ansible_sdk/model/job_status.py
ansible_sdk-1.0.0.dist-info/LICENSE.md
ansible_sdk-1.0.0.dist-info/METADATA
ansible_sdk-1.0.0.dist-info/WHEEL
ansible_sdk-1.0.0.dist-info/pbr.json
ansible_sdk-1.0.0.dist-info/top_level.txt
ansible_sdk-1.0.0.dist-info/RECORD
