Metadata-Version: 2.1
Name: ansible-sdk
Version: 1.0.0
Summary: Consistent Ansible SDK for Python
Author-email: "Ansible, Inc." <info@ansible.com>
Project-URL: Documentation, https://ansible-sdk.readthedocs.io/en/latest/
Project-URL: Source, https://github.com/ansible/ansible-sdk
Classifier: Development Status :: 3 - Alpha
Classifier: Intended Audience :: Developers
Classifier: License :: OSI Approved :: Apache Software License
Classifier: Topic :: Software Development :: Libraries :: Application Frameworks
Classifier: Programming Language :: Python :: 3.9
Classifier: Programming Language :: Python :: 3.10
Requires-Python: >=3.9
License-File: LICENSE.md
Requires-Dist: ansible-core
Requires-Dist: ansible-runner
Requires-Dist: receptorctl
Provides-Extra: doc
Requires-Dist: sphinx ; extra == 'doc'
Provides-Extra: test
Requires-Dist: pytest ; extra == 'test'
